django_handy/__init__.py
django_handy/admin.py
django_handy/attachment.py
django_handy/objs.py
django_handy/redis.py
django_handy/tests.py
django_handy/url.py
django_handy/validation.py
django_handy/models/__init__.py
django_handy/models/atomic.py
django_handy/models/count.py
django_handy/models/expressions.py
django_handy/models/fields.py
django_handy/models/meta.py
django_handy/rest/__init__.py
django_handy/rest/exceptions.py
django_handy/rest/mixins.py
django_handy/rest/pagination.py
django_handy/rest/response.py
django_handy/rest/serializers.py
django_handy-2.3.0.dist-info/AUTHORS.rst
django_handy-2.3.0.dist-info/LICENSE
django_handy-2.3.0.dist-info/METADATA
django_handy-2.3.0.dist-info/WHEEL
django_handy-2.3.0.dist-info/top_level.txt
django_handy-2.3.0.dist-info/RECORD
