Metadata-Version: 2.1
Name: django-handy
Version: 2.3.0
Summary: Set of handy helpers for developing Django web applications.
Home-page: https://github.com/alextatarinov/django-handy
Author: Alexandr Tatarinov
Author-email: tatarinov1997@gmail.com
License: MIT
Keywords: django-handy
Platform: UNKNOWN
Classifier: Development Status :: 5 - Production/Stable
Classifier: Environment :: Web Environment
Classifier: Intended Audience :: Developers
Classifier: License :: OSI Approved :: BSD License
Classifier: Operating System :: OS Independent
Classifier: Programming Language :: Python
Classifier: Programming Language :: Python :: 3
Classifier: Programming Language :: Python :: 3 :: Only
Classifier: Programming Language :: Python :: 3.6
Classifier: Programming Language :: Python :: 3.7
Classifier: Programming Language :: Python :: 3.8
Classifier: Programming Language :: Python :: 3.9
Classifier: Framework :: Django
Classifier: Framework :: Django :: 2.2
Classifier: Framework :: Django :: 3.0
Classifier: Topic :: Software Development :: Libraries :: Python Modules
Requires-Dist: Django (>=2.2)
Requires-Dist: djangorestframework (>=3.9)
Requires-Dist: Pillow
